[{"url": "https://www.youtube.com/watch?v=XtpApcr3QRc", "id": "XtpApcr3QRc", "img": "https://i.ytimg.com/vi/XtpApcr3QRc/default.jpg", "title": "Fanari, Greece - Thrace - AtlasVisual"}, {"url": "https://www.youtube.com/watch?v=cI0zcZtbkZM", "id": "cI0zcZtbkZM", "img": "https://i.ytimg.com/vi/cI0zcZtbkZM/default.jpg", "title": "Larnaca Salt Lake, Cyprus"}, {"url": "https://www.youtube.com/watch?v=8eR-xQRh4Qs", "id": "8eR-xQRh4Qs", "img": "https://i.ytimg.com/vi/8eR-xQRh4Qs/default.jpg", "title": "Wildlife at One Lake Place on the Wetlands"}, {"url": "https://www.youtube.com/watch?v=8MBt6VpE2qI", "id": "8MBt6VpE2qI", "img": "https://i.ytimg.com/vi/8MBt6VpE2qI/default.jpg", "title": "Protecting urban wetlands in NE China"}, {"url": "https://www.youtube.com/watch?v=50F5s09t2qM", "id": "50F5s09t2qM", "img": "https://i.ytimg.com/vi/50F5s09t2qM/default.jpg", "title": "SFWJ: Making South Florida ever-changing water levels meaningful"}, {"url": "https://www.youtube.com/watch?v=S4fmHuftC-Q", "id": "S4fmHuftC-Q", "img": "https://i.ytimg.com/vi/S4fmHuftC-Q/default.jpg", "title": "Santiago Calatrava Margaret Hunt Hill Bridge Dallas first suspension cable installation"}, {"url": "https://www.youtube.com/watch?v=KXpPIla0y84", "id": "KXpPIla0y84", "img": "https://i.ytimg.com/vi/KXpPIla0y84/default.jpg", "title": "RC IOM Racing at Loch Lomond Marina May 22,2011"}]