[{"url": "https://www.youtube.com/watch?v=M3C5xRS2qQc", "id": "M3C5xRS2qQc", "img": "https://i.ytimg.com/vi/M3C5xRS2qQc/default.jpg", "title": "The delta of Axios, Loudias & Aliakmon."}, {"url": "https://www.youtube.com/watch?v=j0MiQkJvfCA", "id": "j0MiQkJvfCA", "img": "https://i.ytimg.com/vi/j0MiQkJvfCA/default.jpg", "title": "RIVER ALIAKMON AFTER RAIN"}, {"url": "https://www.youtube.com/watch?v=EUcOxC4C_NI", "id": "EUcOxC4C_NI", "img": "https://i.ytimg.com/vi/EUcOxC4C_NI/default.jpg", "title": "Eagles Lake Community Park  Naples  9 052013"}, {"url": "https://www.youtube.com/watch?v=bfOFKhbJVjU", "id": "bfOFKhbJVjU", "img": "https://i.ytimg.com/vi/bfOFKhbJVjU/default.jpg", "title": "Vardar River"}]